ts103976/__init__.py
ts103976/console_scripts.py
ts103976/helpers.py
ts103976/lea.py
ts103976/lea_recv.py
ts103976/rps.py
ts103976/validator.py
ts103976/schemas/TS_103_280.schema.json
ts103976/schemas/ts_103120_Authorisation.schema.json
ts103976/schemas/ts_103120_Common.schema.json
ts103976/schemas/ts_103120_Core.schema.json
ts103976/schemas/ts_103120_Delivery.schema.json
ts103976/schemas/ts_103120_Document.schema.json
ts103976/schemas/ts_103120_Notification.schema.json
ts103976/schemas/ts_103120_Task.schema.json
ts103976/schemas/ts_103120_TrafficPolicy.schema.json
ts103976/schemas/ts_103976.schema.json
ts103976-0.1a16.dist-info/entry_points.txt
ts103976-0.1a16.dist-info/LICENSE
ts103976-0.1a16.dist-info/WHEEL
ts103976-0.1a16.dist-info/METADATA
ts103976-0.1a16.dist-info/RECORD
